translatedoc/__init__.py
translatedoc/step1.py
translatedoc/step2.py
translatedoc/translatedoc.py
translatedoc/utils.py
translatedoc-1.6.0.dist-info/METADATA
translatedoc-1.6.0.dist-info/WHEEL
translatedoc-1.6.0.dist-info/entry_points.txt
translatedoc-1.6.0.dist-info/licenses/LICENSE
translatedoc-1.6.0.dist-info/RECORD
