Metadata-Version: 2.4
Name: translatedoc
Version: 1.6.0
Summary: PDFなどのドキュメントを翻訳するツール。
Project-URL: Homepage, https://github.com/ak110/translatedoc
Author-email: "aki." <mark@aur.ll.to>
License-Expression: MIT
License-File: LICENSE
Classifier: Environment :: Console
Classifier: Intended Audience :: Developers
Classifier: Operating System :: OS Independent
Classifier: Programming Language :: Python :: 3 :: Only
Classifier: Topic :: Text Processing
Classifier: Topic :: Utilities
Requires-Python: <4.0,>=3.10
Requires-Dist: markdownify>=0.11
Requires-Dist: openai>=1.10
Requires-Dist: pillow-heif>=0.15
Requires-Dist: pytilpack>=0.2
Requires-Dist: tiktoken>=0.5
Requires-Dist: tqdm
Requires-Dist: unstructured[md]>=0.12
